rsacracker/_init_.py
rsacracker-0.1.0.dist-info/METADATA
rsacracker-0.1.0.dist-info/WHEEL
rsacracker-0.1.0.dist-info/top_level.txt
rsacracker-0.1.0.dist-info/RECORD
