Metadata-Version: 2.4
Name: rsacracker
Version: 0.1.0
Summary: The RSA N Component Cracker is a desktop app that factors a given RSA modulus n into its prime components p and q, where n = p × q. 
Author: neelanjan_manna
Author-email: igi.manna@gmail.com
Classifier: Programming Language :: Python :: 3
Classifier: License :: OSI Approved :: MIT License
Classifier: Operating System :: OS Independent
Requires-Python: >=3.6
Dynamic: author
Dynamic: author-email
Dynamic: classifier
Dynamic: requires-python
Dynamic: summary
